[{
	"name": "전체보기",
	"param": ""
 },
 {
	"name": "중국",
	"param": "country=1"
 },
 {
	"name": "한국",
	"param": "country=2"
 },
 {
	"name": "일본",
	"param": "country=4"
 },
 {
	"name": "미국",
	"param": "country=5"
 },
 {
	"name": "기타국가",
	"param": "country=8"
 },
 {
	"name": "북경",
	"param": "country=1&province=1"
 },
 {
	"name": "광주",
	"param": "country=1&province=5&city=1"
 },
 {
	"name": "상해",
	"param": "country=1&province=2"
 },
 {
	"name": "연길",
	"param": "country=1&province=17&city=11"
 },
 {
	"name": "천진",
	"param": "country=1&province=3"
 },
 {
	"name": "심천",
	"param": "country=1&province=5&city=2"
 },
 {
	"name": "청도",
	"param": "country=1&province=24&city=2"
 },
 {
	"name": "대련",
	"param": "country=1&province=20&city=4"
 },
 {
	"name": "심양",
	"param": "country=1&province=20&city=1"
 },
 {
	"name": "위해",
	"param": "country=1&province=24&city=15"
 },
 {
	"name": "장춘",
	"param": "country=1&province=17&city=1"
 },
 {
	"name": "소주",
	"param": "country=1&province=18&city=4"
 },
 {
	"name": "연태",
	"param": "country=1&province=24&city=4"
 },
 {
	"name": "동관",
	"param": "country=1&province=5&city=15"
 },
 {
	"name": "할빈",
	"param": "country=1&province=14&city=1"
 },
 {
	"name": "이우",
	"param": "country=1&province=31&city=22"
 },
 {
	"name": "조선",
	"param": "country=3"
 },
 {
	"name": "러시아",
	"param": "country=6"
 },
 {
	"name": "몽골",
	"param": "country=7"
 }
]